iotics_auth/__init__.py
iotics_auth/identity.py
tests/__init__.py
tests/test_identity.py
iotics_auth-0.1.0.dist-info/LICENSE
iotics_auth-0.1.0.dist-info/METADATA
iotics_auth-0.1.0.dist-info/WHEEL
iotics_auth-0.1.0.dist-info/top_level.txt
iotics_auth-0.1.0.dist-info/RECORD
