Metadata-Version: 2.1
Name: iotics_auth
Version: 0.1.0
Summary: A library for IOTICS identity management
Author: gaurav ms
Author-email: datascientist.msgaurav@gmail.com
Classifier: Programming Language :: Python :: 3
Classifier: License :: OSI Approved :: MIT License
Classifier: Operating System :: OS Independent
Requires-Python: >=3.6
License-File: LICENSE
Requires-Dist: numpy
Requires-Dist: pandas
Requires-Dist: matplotlib
Requires-Dist: requests
Requires-Dist: iotics-identity
Requires-Dist: iotics-grpc-client
